rapidcaptcha/__init__.py
rapidcaptcha/client.py
rapidcaptcha-1.0.0.dist-info/licenses/LICENSE
tests/__init__.py
tests/test_async.py
tests/test_client.py
tests/test_errors.py
rapidcaptcha-1.0.0.dist-info/METADATA
rapidcaptcha-1.0.0.dist-info/WHEEL
rapidcaptcha-1.0.0.dist-info/top_level.txt
rapidcaptcha-1.0.0.dist-info/RECORD
