Metadata-Version: 2.4
Name: rapidcaptcha
Version: 1.0.0
Summary: Official Python SDK for RapidCaptcha API
Home-page: https://github.com/RapidCaptcha-SDK/RapidCaptcha-Python
Author: Galkurta
Author-email: RapidCaptcha Team <support@rapidcaptcha.xyz>
License: MIT
Project-URL: Homepage, https://rapidcaptcha.xyz
Project-URL: Documentation, https://docs.rapidcaptcha.xyz
Project-URL: Repository, https://github.com/RapidCaptcha-SDK/RapidCaptcha-Python
Project-URL: Bug Tracker, https://github.com/RapidCaptcha-SDK/RapidCaptcha-Python/issues
Classifier: Development Status :: 5 - Production/Stable
Classifier: Intended Audience :: Developers
Classifier: License :: OSI Approved :: MIT License
Classifier: Programming Language :: Python :: 3
Classifier: Programming Language :: Python :: 3.7
Classifier: Programming Language :: Python :: 3.8
Classifier: Programming Language :: Python :: 3.9
Classifier: Programming Language :: Python :: 3.10
Classifier: Programming Language :: Python :: 3.11
Classifier: Programming Language :: Python :: 3.12
Requires-Python: >=3.7
License-File: LICENSE
Requires-Dist: requests>=2.25.0
Provides-Extra: async
Requires-Dist: aiohttp>=3.8.0; extra == "async"
Provides-Extra: dev
Requires-Dist: pytest>=6.0; extra == "dev"
Requires-Dist: pytest-asyncio>=0.18.0; extra == "dev"
Requires-Dist: pytest-cov>=3.0.0; extra == "dev"
Requires-Dist: black>=22.0; extra == "dev"
Requires-Dist: flake8>=4.0; extra == "dev"
Requires-Dist: mypy>=0.950; extra == "dev"
Requires-Dist: pre-commit>=2.15.0; extra == "dev"
Requires-Dist: bandit>=1.7.0; extra == "dev"
Requires-Dist: safety>=2.0.0; extra == "dev"
Provides-Extra: test
Requires-Dist: pytest>=6.0; extra == "test"
Requires-Dist: pytest-asyncio>=0.18.0; extra == "test"
Requires-Dist: pytest-mock>=3.6.0; extra == "test"
Requires-Dist: pytest-cov>=3.0.0; extra == "test"
Requires-Dist: responses>=0.18.0; extra == "test"
Requires-Dist: aioresponses>=0.7.0; extra == "test"
Dynamic: author
Dynamic: home-page
Dynamic: license-file
Dynamic: requires-python
